bitcointx/__init__.py
bitcointx/base58.py
bitcointx/bech32.py
bitcointx/rpc.py
bitcointx/segwit_addr.py
bitcointx/signmessage.py
bitcointx/wallet.py
bitcointx/core/__init__.py
bitcointx/core/_bignum.py
bitcointx/core/key.py
bitcointx/core/script.py
bitcointx/core/scripteval.py
bitcointx/core/serialize.py
bitcointx/tests/__init__.py
bitcointx/tests/test_base58.py
bitcointx/tests/test_bech32.py
bitcointx/tests/test_checkblock.py
bitcointx/tests/test_core.py
bitcointx/tests/test_hd_keys.py
bitcointx/tests/test_key.py
bitcointx/tests/test_rpc.py
bitcointx/tests/test_script.py
bitcointx/tests/test_scripteval.py
bitcointx/tests/test_segwit.py
bitcointx/tests/test_serialize.py
bitcointx/tests/test_signmessage.py
bitcointx/tests/test_transactions.py
bitcointx/tests/test_wallet.py
asimov_lib-0.10.4.dev0.dist-info/LICENSE
asimov_lib-0.10.4.dev0.dist-info/METADATA
asimov_lib-0.10.4.dev0.dist-info/WHEEL
asimov_lib-0.10.4.dev0.dist-info/top_level.txt
asimov_lib-0.10.4.dev0.dist-info/RECORD
