Metadata-Version: 2.1
Name: asimov-lib
Version: 0.10.4.dev0
Summary: The Swiss Army Knife of the Bitcoin protocol.
Home-page: https://github.com/BlockGeeks0x01/asimov-lib
Author: eric sun
Author-email: ericsgy@163.com
License: UNKNOWN
Keywords: bitcoin
Platform: UNKNOWN
Classifier: Programming Language :: Python :: 3
Classifier: License :: OSI Approved :: GNU Lesser General Public License v3 or later (LGPLv3+)
Requires-Python: >=3.4
